sbanetwork/__init__.py
sbanetwork/core/__init__.py
sbanetwork/core/activations.py
sbanetwork/core/backprop.py
sbanetwork/core/batchnorm.py
sbanetwork/core/callbacks.py
sbanetwork/core/initializers.py
sbanetwork/core/layers.py
sbanetwork/core/losses.py
sbanetwork/core/model.py
sbanetwork/core/optimizers.py
sbanetwork/core/regularizers.py
sbanetwork/core/utils.py
sbanetwork-0.1.3.dist-info/METADATA
sbanetwork-0.1.3.dist-info/WHEEL
sbanetwork-0.1.3.dist-info/top_level.txt
sbanetwork-0.1.3.dist-info/RECORD
