Metadata-Version: 2.1
Name: sbanetwork
Version: 0.1.3
Summary: Lightweight Neural Network Library from scratch
Author: Abhishek Gupta
Classifier: Programming Language :: Python :: 3
Classifier: License :: OSI Approved :: MIT License
Classifier: Operating System :: OS Independent
Requires-Python: >=3.6
Requires-Dist: numpy
